poku/__init__.py
poku/__main__.py
poku/buku.py
poku/exceptions.py
poku/pocket.py
poku/poku.py
poku/utils.py
poku-0.1.3.dist-info/AUTHORS.rst
poku-0.1.3.dist-info/LICENSE
poku-0.1.3.dist-info/METADATA
poku-0.1.3.dist-info/WHEEL
poku-0.1.3.dist-info/entry_points.txt
poku-0.1.3.dist-info/top_level.txt
poku-0.1.3.dist-info/RECORD
