Metadata-Version: 2.1
Name: poku
Version: 0.1.3
Summary: Symmetrical sync between pocket and buku
Home-page: https://github.com/shanedonohoe/poku
Author: Shane Donohoe
Author-email: shane@isda.best
License: GNU General Public License v3
Keywords: poku
Platform: UNKNOWN
Classifier: Development Status :: 2 - Pre-Alpha
Classifier: Intended Audience :: Developers
Classifier: License :: OSI Approved :: GNU General Public License v3 (GPLv3)
Classifier: Natural Language :: English
Classifier: Programming Language :: Python :: 3
Classifier: Programming Language :: Python :: 3.6
Classifier: Programming Language :: Python :: 3.7
Requires-Dist: buku
Requires-Dist: requests
Requires-Dist: ConfigArgParse
